{"nome":"Riccardo","cognome":"Molina","immagine":"../roster/images/riccardo_molina.jpg","bio":"Comincia a giocare in quarta elementare per emulare il fratello maggiore. Passa per tutta la trafila delle giovanili nella squadra della sua scuola Leonardo da Vinci: minibasket, ragazzi, cadetti, juniores (i bei vecchi tempi dell'epoca pre-under) e diventa aggregato alla squadra senior della Kronos LDV Catania in C2 (ovviamente tra panchina - portaborse/borracce e tribuna). Si concede una breve pausa dallo sport durante gli anni di "studio" dell'università, ma nel 2005 il trasferimento a Bologna per lavoro è propizio per riprendere: fino al 2018 non si ferma mai: tra Forti e Liberi, Nova Basket Castenaso e Santa Maria di Fossolo passa qualche anno tra Promozione e Prima Divisione FIP, prima di passare al basket che conta in CSI. Si trasferisce a Milano nel 2018 e la prima cosa che fa, ancora prima di cercare casa, è cercare una squadra che lo accolga: passa un'annata strana in CSI a Cassina de Pecchi, prima di trovare una nuova casa definitiva nel 2019/20 da quelli che quella stagione avrebbero preso il nome di Brewers, trovando un gruppo di persone che, come lui, quando gioca a basket è felice. Ovviamente la felicità in questione, termina quando incontra gli arbitri: "Un tempo la mia specialità era la difesa, oggi è sventolare asciugamani e intrattenere con gli arbitri conversazioni filosofiche sulla difficoltà di giudicare l'attività altrui e sull'innata fallacia dell'essere umano: nonostante le mie inattaccabili argomentazioni, spesso ottengo come risposta un'unica parola: "Tecnico"." Riccardo Molina, cit. 2024.","statistiche":{"minuti":0,"punti":0,"rimbalzi":0,"assist":0,"rubate":0,"stoppate":0},"video": [] }